nam/__init__.py
nam/_core.py
nam/_handshake.py
nam/_version.py
nam/cli.py
nam/data.py
nam/util.py
nam/_dependencies/__init__.py
nam/_dependencies/auraloss/LICENSE
nam/_dependencies/auraloss/__init__.py
nam/_dependencies/auraloss/freq.py
nam/_dependencies/auraloss/perceptual.py
nam/_dependencies/auraloss/plotting.py
nam/_dependencies/auraloss/time.py
nam/_dependencies/auraloss/utils.py
nam/models/__init__.py
nam/models/_abc.py
nam/models/_activations.py
nam/models/_from_nam.py
nam/models/_names.py
nam/models/base.py
nam/models/conv_net.py
nam/models/exportable.py
nam/models/linear.py
nam/models/losses.py
nam/models/metadata.py
nam/models/recurrent.py
nam/models/wavenet.py
nam/models/_resources/loudness_input.wav
nam/train/__init__.py
nam/train/_names.py
nam/train/_version.py
nam/train/colab.py
nam/train/core.py
nam/train/full.py
nam/train/lightning_module.py
nam/train/metadata.py
nam/train/gui/__init__.py
nam/train/gui/_resources/__init__.py
nam/train/gui/_resources/settings.py
neural_amp_modeler-0.12.2.dist-info/licenses/LICENSE
neural_amp_modeler-0.12.2.dist-info/METADATA
neural_amp_modeler-0.12.2.dist-info/WHEEL
neural_amp_modeler-0.12.2.dist-info/entry_points.txt
neural_amp_modeler-0.12.2.dist-info/top_level.txt
neural_amp_modeler-0.12.2.dist-info/RECORD
