Metadata-Version: 2.4
Name: neural-amp-modeler
Version: 0.12.2
Summary: Neural Amp Modeler
Author-email: Steven Atkinson <steven@atkinson.mn>
License: MIT License
Project-URL: homepage, https://github.com/sdatkinson/
Requires-Python: >=3.9
License-File: LICENSE
Requires-Dist: librosa
Requires-Dist: matplotlib
Requires-Dist: numpy
Requires-Dist: pydantic>=2.0.0
Requires-Dist: pytorch_lightning
Requires-Dist: scipy
Requires-Dist: sounddevice
Requires-Dist: tensorboard
Requires-Dist: torch
Requires-Dist: transformers>=4
Requires-Dist: tqdm
Requires-Dist: wavio>=0.0.5
Provides-Extra: transformers-compat
Requires-Dist: transformers>=4; extra == "transformers-compat"
Requires-Dist: numpy; extra == "transformers-compat"
Provides-Extra: test
Requires-Dist: pytest; extra == "test"
Requires-Dist: pytest-mock; extra == "test"
Requires-Dist: requests; extra == "test"
Dynamic: license-file
